napari_psf_analysis/__init__.py
napari_psf_analysis/_dock_widget.py
napari_psf_analysis/_version.py
napari_psf_analysis/napari.yaml
napari_psf_analysis/_tests/__init__.py
napari_psf_analysis/_tests/test_dock_widget.py
napari_psf_analysis/_tests/psf_analysis/__init__.py
napari_psf_analysis/_tests/psf_analysis/test_analyzer.py
napari_psf_analysis/_tests/psf_analysis/test_psf.py
napari_psf_analysis/_tests/psf_analysis/test_utils.py
napari_psf_analysis/_tests/psf_analysis/extract/__init__.py
napari_psf_analysis/_tests/psf_analysis/extract/test_BeadExtractor.py
napari_psf_analysis/_tests/psf_analysis/fit/__init__.py
napari_psf_analysis/_tests/psf_analysis/fit/test_fit_1d.py
napari_psf_analysis/_tests/psf_analysis/fit/test_fit_2d.py
napari_psf_analysis/_tests/psf_analysis/fit/test_fit_3d.py
napari_psf_analysis/_tests/psf_analysis/fit/test_fitter.py
napari_psf_analysis/psf_analysis/__init__.py
napari_psf_analysis/psf_analysis/analyzer.py
napari_psf_analysis/psf_analysis/image.py
napari_psf_analysis/psf_analysis/parameters.py
napari_psf_analysis/psf_analysis/psf.py
napari_psf_analysis/psf_analysis/records.py
napari_psf_analysis/psf_analysis/sample.py
napari_psf_analysis/psf_analysis/utils.py
napari_psf_analysis/psf_analysis/extract/BeadExtractor.py
napari_psf_analysis/psf_analysis/extract/__init__.py
napari_psf_analysis/psf_analysis/fit/__init__.py
napari_psf_analysis/psf_analysis/fit/estimator.py
napari_psf_analysis/psf_analysis/fit/fit_1d.py
napari_psf_analysis/psf_analysis/fit/fit_2d.py
napari_psf_analysis/psf_analysis/fit/fit_3d.py
napari_psf_analysis/psf_analysis/fit/fitter.py
napari_psf_analysis/resources/logo.png
napari_psf_analysis/resources/logo.svg
napari_psf_analysis-1.1.4.dist-info/LICENSE
napari_psf_analysis-1.1.4.dist-info/METADATA
napari_psf_analysis-1.1.4.dist-info/WHEEL
napari_psf_analysis-1.1.4.dist-info/entry_points.txt
napari_psf_analysis-1.1.4.dist-info/top_level.txt
napari_psf_analysis-1.1.4.dist-info/RECORD
