Metadata-Version: 2.1
Name: napari_psf_analysis
Version: 1.1.4
Summary: A plugin to analyse point spread functions (PSFs).
Home-page: https://github.com/fmi-faim/napari-psf-analysis.git
Author: Tim-Oliver Buchholz
Author-email: tim-oliver.buchholz@fmi.ch
License: BSD-3-Clause
Project-URL: Bug Tracker, https://github.com/fmi-faim/napari-psf-analysis/issues
Project-URL: Documentation, https://github.com/fmi-faim/napari-psf-analysis#README.md
Project-URL: Source Code, https://github.com/fmi-faim/napari-psf-analysis
Project-URL: User Support, https://github.com/fmi-faim/napari-psf-analysis/issues
Classifier: Development Status :: 3 - Alpha
Classifier: Framework :: napari
Classifier: Intended Audience :: Developers
Classifier: License :: OSI Approved :: BSD License
Classifier: Operating System :: OS Independent
Classifier: Programming Language :: Python
Classifier: Programming Language :: Python :: 3
Classifier: Programming Language :: Python :: 3 :: Only
Classifier: Topic :: Software Development :: Testing
Requires-Python: >=3.9
License-File: LICENSE
Requires-Dist: bfio
Requires-Dist: matplotlib<3.9
Requires-Dist: matplotlib-scalebar
Requires-Dist: napari
Requires-Dist: numpy
Requires-Dist: pandas
Requires-Dist: scikit-image
Provides-Extra: testing
Requires-Dist: napari; extra == "testing"
Requires-Dist: pyqt5; extra == "testing"
Requires-Dist: pytest; extra == "testing"
Requires-Dist: pytest-cov; extra == "testing"
Requires-Dist: pytest-qt; extra == "testing"
Requires-Dist: tox; extra == "testing"
